pickle_utils/__init__.py
pickle_utils-0.1.1.dist-info/LICENSE.txt
pickle_utils-0.1.1.dist-info/METADATA
pickle_utils-0.1.1.dist-info/WHEEL
pickle_utils-0.1.1.dist-info/top_level.txt
pickle_utils-0.1.1.dist-info/RECORD
