Metadata-Version: 2.1
Name: pickle-utils
Version: 0.1.1
Summary: Memoize functions to disk, load and save compressed Pickle files.
Home-page: https://pypi.org/project/pickle_utils/
Author: Adrià Garriga-Alonso
Author-email: adria.garriga@gmail.com
License: UNKNOWN
Download-URL: https://github.com/rhaps0dy/pickle_utils/archive/0.1.1.tar.gz
Keywords: pickle
Platform: UNKNOWN
Classifier: Programming Language :: Python :: 3
Classifier: License :: OSI Approved :: MIT License
Classifier: Operating System :: OS Independent
Requires-Dist: pandas (>=1.0)
